jaxutils/__init__.py
jaxutils/_version.py
jaxutils/config.py
jaxutils/data.py
jaxutils/dict.py
jaxutils/parameters.py
jaxutils/pytree.py
jaxutils_nightly-0.0.8.dev20250331.dist-info/LICENSE
jaxutils_nightly-0.0.8.dev20250331.dist-info/METADATA
jaxutils_nightly-0.0.8.dev20250331.dist-info/WHEEL
jaxutils_nightly-0.0.8.dev20250331.dist-info/top_level.txt
jaxutils_nightly-0.0.8.dev20250331.dist-info/RECORD
