Metadata-Version: 2.1
Name: jaxutils-nightly
Version: 0.0.8.dev20250331
Summary: Utility functions for JaxGaussianProcesses
Home-page: UNKNOWN
Author: Daniel Dodd and Thomas Pinder
Author-email: tompinder@live.co.uk
License: LICENSE
Project-URL: Documentation, https://JaxUitls.readthedocs.io/en/latest/
Project-URL: Source, https://github.com/JaxGaussianProcesses/JaxUitls
Keywords: gaussian-processes jax machine-learning bayesian
Platform: UNKNOWN
Requires-Dist: jax (>=0.4.0)
Requires-Dist: jaxlib (>=0.4.0)
Requires-Dist: jaxtyping
Requires-Dist: ml-collections (==0.1.0)
Requires-Dist: distrax (>=0.1.2)
Provides-Extra: cuda
Requires-Dist: jax[cuda] ; extra == 'cuda'
Provides-Extra: dev
Requires-Dist: black ; extra == 'dev'
Requires-Dist: isort ; extra == 'dev'
Requires-Dist: pylint ; extra == 'dev'
Requires-Dist: flake8 ; extra == 'dev'
Requires-Dist: pytest ; extra == 'dev'
Requires-Dist: pytest-cov ; extra == 'dev'
